{
  "parent": "minecraft:recipes/root",
  "rewards": {
    "recipes": [
      "morethanapickaxe:adamantium_adze"
    ]
  },
  "criteria": {
    "has_adamantium": {
      "trigger": "minecraft:inventory_changed",
      "conditions": {
        "items": [
          {
            "items": [
              "adabraniummod:adamantium_ingot"
            ]
          }
        ]
      }
    },
    "has_the_recipe": {
      "trigger": "minecraft:recipe_unlocked",
      "conditions": {
        "recipe": "morethanapickaxe:adamantium_adze"
      }
    }
  },
  "requirements": [
    [
      "has_adamantium",
      "has_the_recipe"
    ]
  ]
}