{
  "parent": "minecraft:recipes/root",
  "rewards": {
    "recipes": [
      "morethanapickaxe:tanzanite_adze_vanillaenhanced"
    ]
  },
  "criteria": {
    "has_tanzanite": {
      "trigger": "minecraft:inventory_changed",
      "conditions": {
        "items": [
          {
            "items": [
              "vanillaenhanced:tanzanite"
            ]
          }
        ]
      }
    },
    "has_the_recipe": {
      "trigger": "minecraft:recipe_unlocked",
      "conditions": {
        "recipe": "morethanapickaxe:tanzanite_adze_vanillaenhanced"
      }
    }
  },
  "requirements": [
    [
      "has_tanzanite",
      "has_the_recipe"
    ]
  ]
}